[

	{
		"title": "Let's Talk at Lunch",
		"start": "2016-01-19T12:00:00-06:00",
		"url": "/events/2016/01/19/lets-talk-at-lunch",
		"className": "workshop"
	},

	{
		"title": "Morning Matinee: Frida",
		"start": "2016-01-21T10:30:00-06:00",
		"url": "/events/2016/01/21/morning-matinee-frida",
		"className": "film"
	},

	{
		"title": "Books in the Woods: The Book of Unknown Americans",
		"start": "2016-01-25T19:30:00-06:00",
		"url": "/events/2016/01/25/books-in-the-woods-the-book-of-unknown-americans",
		"className": "books-authors"
	},

	{
		"title": "US Latino/as: Languages, Hybrid Identities and Poetry",
		"start": "2016-01-28T19:00:00-06:00",
		"url": "/events/2016/01/28/us-latino-as-languages-hybrid-identities-and-poetry",
		"className": "lecture"
	},

	{
		"title": "Opening Event",
		"start": "2016-01-31T13:00:00-06:00",
		"url": "/events/2016/01/31/opening-event",
		"className": "performance"
	},

	{
		"title": "The Motorcycle Diaries",
		"start": "2016-02-02T14:00:00-06:00",
		"url": "/events/2016/02/02/movie-the-motorcycle-diaries",
		"className": "film"
	},

	{
		"title": "Spotlight on Latino Writers",
		"start": "2016-02-03T13:00:00-06:00",
		"url": "/events/2016/02/03/spotlight-on-latino-writers",
		"className": "books-authors"
	},

	{
		"title": "Book Discussion: The Book of Unknown Americans",
		"start": "2016-02-04T13:00:00-06:00",
		"url": "/events/2016/02/04/book-discussion-the-book-of-unknown-americans",
		"className": "books-authors"
	},

	{
		"title": "McFarland USA",
		"start": "2016-02-05T18:00:00-06:00",
		"url": "/events/2016/02/05/mcfarland-usa",
		"className": "film"
	},

	{
		"title": "¡Viva! Dream and Drum ",
		"start": "2016-02-06T10:00:00-06:00",
		"url": "/events/2016/02/06/viva-dream-and-drum",
		"className": "kids-family"
	},

	{
		"title": "Samuel Del Real Latin Jazz Trio Concert",
		"start": "2016-02-07T14:00:00-06:00",
		"url": "/events/2016/02/07/samuel-del-real-latin-jazz-trio-concert",
		"className": "performance"
	},

	{
		"title": "Book Discussion: The Book of Unknown Americans",
		"start": "2016-02-08T11:00:00-06:00",
		"url": "/events/2016/02/08/book-discussion-the-book-of-unknown-americans",
		"className": "books-authors"
	},

	{
		"title": "Appetizers & Artist Talk at 90 Miles Cuban Caf&eacute;",
		"start": "2016-02-09T17:00:00-06:00",
		"url": "/events/2016/02/09/appetizers-artist-talk-at-90-miles",
		"className": "workshop"
	},

	{
		"title": "Raising Children in Bilingual Households",
		"start": "2016-02-10T18:30:00-06:00",
		"url": "/events/2016/02/10/raising-children-in-bilingual-households",
		"className": "kids-family"
	},

	{
		"title": "Bilingual Book Discussion: The Book of Unknown Americans / El Libro de los Americanos Desconocidos",
		"start": "2016-02-11T18:30:00-06:00",
		"url": "/events/2016/02/11/bilingual-book-discussion-the-book-of-unknown-americans-el-libro-de-los-americanos-desconocidos",
		"className": "bilingual"
	},

	{
		"title": "Segundo Sabado Loteria",
		"start": "2016-02-13T09:30:00-06:00",
		"url": "/events/2016/02/13/segundo-sabado-loteria",
		"className": "kids-family"
	},

	{
		"title": "Los Hermanos Escamilla Trick Rope Show",
		"start": "2016-02-14T14:00:00-06:00",
		"url": "/events/2016/02/14/los-hermanos-escamilla-trick-rope-show",
		"className": "kids-family"
	},

	{
		"title": "Identities as Multiplicities and New Configurations ",
		"start": "2016-02-15T17:00:00-06:00",
		"url": "/events/2016/02/15/identities-as-multiplicities-and-new-configurations",
		"className": "lecture"
	},

	{
		"title": "Let's Talk at Lunch",
		"start": "2016-02-16T12:00:00-06:00",
		"url": "/events/2016/02/16/lets-talk-at-lunch",
		"className": "workshop"
	},

	{
		"title": "Movie: The Sea Inside",
		"start": "2016-02-16T14:00:00-06:00",
		"url": "/events/2016/02/16/movie-the-sea-inside",
		"className": "film"
	},

	{
		"title": "Wrap it up: Tamales and Pasteles",
		"start": "2016-02-16T19:00:00-06:00",
		"url": "/events/2016/02/16/wrap-it-up-tamales-and-pasteles",
		"className": "workshop"
	},

	{
		"title": "Chef Demo with Live Music",
		"start": "2016-02-17T11:15:00-06:00",
		"url": "/events/2016/02/17/chef-demo-with-live-music",
		"className": "workshop"
	},

	{
		"title": "The Iberian Inquisition comes to the Americas",
		"start": "2016-02-17T16:00:00-06:00",
		"url": "/events/2016/02/17/the-iberian-inquisition-comes-to-the-americas",
		"className": "lecture"
	},

	{
		"title": "Between the Lines' Book Discussion Group: The Book of Unknown Americans",
		"start": "2016-02-18T10:00:00-06:00",
		"url": "/events/2016/02/18/between-the-lines-book-discussion-group-the-book-of-unknown-americans",
		"className": "books-authors"
	},

	{
		"title": "A presentation by Dr. Sherwin Bryant",
		"start": "2016-02-18T16:00:00-06:00",
		"url": "/events/2016/02/18/a-presentation-by-dr-sherwin-bryant",
		"className": "lecture"
	},

	{
		"title": "Book Discussion: Illegal by José Ángel N.",
		"start": "2016-02-18T19:00:00-06:00",
		"url": "/events/2016/02/18/book-discussion-illegal-by-jose-angel-n",
		"className": "books-authors"
	},

	{
		"title": "Cantar y Jugar with CATS Music",
		"start": "2016-02-20T10:30:00-06:00",
		"url": "/events/2016/02/20/cantar-y-jugar-with-cats-music",
		"className": "kids-family"
	},

	{
		"title": "Meet the Artist: Alfonso Piloto Nieves Ruiz",
		"start": "2016-02-22T18:00:00-06:00",
		"url": "/events/2016/02/22/meet-the-artist-alfonso-piloto-nieves-ruiz",
		"className": "workshop"
	},

	{
		"title": "Between the Lines' Book Discussion Group: The Book of Unknown Americans",
		"start": "2016-02-23T19:00:00-06:00",
		"url": "/events/2016/02/23/between-the-lines-book-discussion-group-the-book-of-unknown-americans",
		"className": "books-authors"
	},

	{
		"title": "Book Discussion: The Book of Unknown Americans",
		"start": "2016-02-23T19:00:00-06:00",
		"url": "/events/2016/02/23/book-discussion-the-book-of-unknown-americans",
		"className": "books-authors"
	},

	{
		"title": "Taste of Ecuador",
		"start": "2016-02-24T18:00:00-06:00",
		"url": "/events/2016/02/24/taste-of-ecuador",
		"className": "workshop"
	},

	{
		"title": "Abuela's Stories: A Time of Magic",
		"start": "2016-02-25T18:30:00-06:00",
		"url": "/events/2016/02/25/abuelas-stories",
		"className": "kids-family"
	},

	{
		"title": "Uncharted Territory: Narratives on Latino Migration",
		"start": "2016-02-25T19:00:00-06:00",
		"url": "/events/2016/02/25/uncharted-territory-narratives-on-latino-migration",
		"className": "books-authors"
	},

	{
		"title": "Create Mola! Panamanian Inspired Folk Art",
		"start": "2016-02-26T16:30:00-06:00",
		"url": "/events/2016/02/26/create-mola-panamanian-inspired-folk-art",
		"className": "kids-family"
	},

	{
		"title": "Book Discussion: Into the Beautiful North",
		"start": "2016-02-27T11:00:00-06:00",
		"url": "/events/2016/02/27/book-discussion-into-the-beautiful-north",
		"className": "books-authors"
	},

	{
		"title": "The Many Tastes of Salsa",
		"start": "2016-02-27T14:30:00-06:00",
		"url": "/events/2016/02/27/the-many-tastes-of-salsa",
		"className": "kids-family"
	},

	{
		"title": "Kaia String Quartet",
		"start": "2016-02-28T15:00:00-06:00",
		"url": "/events/2016/02/28/kaia-string-quartet",
		"className": "performance"
	},

	{
		"title": "Hora de Cuentos/Bilingual Storytime",
		"start": "2016-02-29T10:30:00-06:00",
		"url": "/events/2016/02/29/hora-de-cuentos-bilingual-storytime",
		"className": "kids-family"
	},

	{
		"title": "A Very Special Listen Up!: Drum Dream Girl",
		"start": "2016-03-01T10:00:00-06:00",
		"url": "/events/2016/03/01/a-very-special-listen-up-drum-dream-girl",
		"className": "kids-family"
	},

	{
		"title": "Taste of Ecuador",
		"start": "2016-03-02T18:00:00-06:00",
		"url": "/events/2016/03/02/taste-of-ecuador",
		"className": "workshop"
	},

	{
		"title": "Gendered geographies of citizenship amongst Central American activists in Los Angeles",
		"start": "2016-03-03T17:00:00-06:00",
		"url": "/events/2016/03/03/lecture-gendered-geographies-of-citizenship-amongst-central-american-activists-in-los-angeles",
		"className": "lecture"
	},

	{
		"title": "Evening of Latino and Hispanic Culture",
		"start": "2016-03-03T18:30:00-06:00",
		"url": "/events/2016/03/03/evening-of-latino-and-hispanic-culture",
		"className": "workshop"
	},

	{
		"title": "DIY Teen Craft: Guatemalan Worry Dolls",
		"start": "2016-03-04T16:00:00-06:00",
		"url": "/events/2016/03/04/diy-teen-craft-guatemalan-worry-dolls",
		"className": "workshop"
	},

	{
		"title": "Visit the National Museum of Mexican Arts",
		"start": "2016-03-05T10:00:00-06:00",
		"url": "/events/2016/03/05/visit-the-national-museum-of-mexican-arts",
		"className": "workshop"
	},

	{
		"title": "Latino Film Screening and Discussion: East Side Sushi",
		"start": "2016-03-06T14:00:00-06:00",
		"url": "/events/2016/03/06/latino-film-screening-and-discussion-east-side-sushi",
		"className": "film"
	},

	{
		"title": "Hora de Cuentos/Bilingual Storytime",
		"start": "2016-03-07T10:30:00-06:00",
		"url": "/events/2016/03/07/hora-de-cuentos-bilingual-storytime",
		"className": "kids-family"
	},

	{
		"title": "Evanston Public Library's Big Read Keynote: Luis Alberto Urrea",
		"start": "2016-03-09T19:00:00-06:00",
		"url": "/events/2016/03/09/lecture-evanston-public-librarys-big-read-keynote-luis-alberto-urrea",
		"className": "lecture"
	},

	{
		"title": "Sumak Kawsay and Suma Qama: Learning about and from the indigenous communities of Bolivia and Peru",
		"start": "2016-03-10T14:00:00-06:00",
		"url": "/events/2016/03/10/sumak-kawsay-and-suma-qama-learning-about-and-from-the-indigenous-communities-of-bolivia-and-peru",
		"className": "lecture"
	},

	{
		"title": "Salsa Night at 90 Miles Cuban Cafe, Lincolnwood Town Center",
		"start": "2016-03-10T18:00:00-06:00",
		"url": "/events/2016/03/10/viva-salsa-night-at-lincolnwood-mall-live-salsa-band",
		"className": "performance"
	},

	{
		"title": "World Language Storytime: Spanish",
		"start": "2016-03-11T18:00:00-06:00",
		"url": "/events/2016/03/11/world-language-storytime-spanish",
		"className": "kids-family"
	},

	{
		"title": "Crafty Saturday",
		"start": "2016-03-12T09:30:00-06:00",
		"url": "/events/2016/03/12/crafty-saturday",
		"className": "kids-family"
	},

	{
		"title": "Sounds of Brazil with Dedé Sampaio",
		"start": "2016-03-12T14:00:00-06:00",
		"url": "/events/2016/03/12/sounds-of-brazil-with-dede-sampaio",
		"className": "performance"
	},

	{
		"title": "Salsa in America: Discussion and Performance",
		"start": "2016-03-21T13:00:00-05:00",
		"url": "/events/2016/03/21/salsa-in-america-discussion-and-performance",
		"className": "performance"
	},

	{
		"title": "Precious Knowledge Documentary and Discussion",
		"start": "2016-03-21T17:00:00-05:00",
		"url": "/events/2016/03/21/precious-knowledge-documentary-and-discussion",
		"className": "film"
	},

	{
		"title": "Precious Knowledge Documentary and Discussion",
		"start": "2016-03-23T17:00:00-05:00",
		"url": "/events/2016/03/23/precious-knowledge-documentary-and-discussion",
		"className": "film"
	},

	{
		"title": "Book Discussion: The Book of Unknown Americans",
		"start": "2016-03-31T13:00:00-05:00",
		"url": "/events/2016/03/31/book-discussion-the-book-of-unknown-americans",
		"className": "books-author"
	},

	{
		"title": "Juegos y Jugetes Tradicionales (Games and Traditional Toys)",
		"start": "2016-04-22T19:00:00-05:00",
		"url": "/events/2016/04/22/games-traditional-toys-juegos-y-jugetes-tradicionales",
		"className": "kids-family"
	},

	{
		"title": "Stand Against Racism",
		"start": "2016-04-29T10:35:00-05:00",
		"url": "/events/2016/04/29/stand-against-racism",
		"className": "workshop"
	},

	{
		"title": "Dinner and a Movie  The Book of Life",
		"start": "2016-04-29T20:30:00-05:00",
		"url": "/events/2016/04/29/dinner-and-a-movie-the-book-of-life",
		"className": "workshop"
	},

	{
		"title": "La Historia y El Uso del Rebozo (History and use of the Shawl)",
		"start": "2016-05-13T19:00:00-05:00",
		"url": "/events/2016/05/13/la-historia-y-el-uso-del-rebozo-history-and-use-of-the-shawl",
		"className": "workshop"
	}

]
